[{"author":"chrosky","url":"https:\/\/youtu.be\/Nxj8gheB7pw","image":"https:\/\/cdn.discordapp.com\/attachments\/936396023478243389\/936397859283165305\/Chrosky.png"},{"author":"chrosky","url":"https:\/\/www.youtube.com\/watch?v=JB4jZlu2-rI","image":"https:\/\/cdn.discordapp.com\/attachments\/936396023478243389\/936397865327145020\/Chrosky_2.png"},{"author":"morning","url":"https:\/\/www.youtube.com\/watch?v=KsV9dbDudoM","image":"https:\/\/cdn.discordapp.com\/attachments\/936396023478243389\/936396778423582730\/Morning.png"},{"author":"morning","url":"https:\/\/youtu.be\/zarF50ByiIU","image":"https:\/\/cdn.discordapp.com\/attachments\/936396023478243389\/936396778696228904\/Morning2.png"},{"author":"kronk","url":"https:\/\/www.youtube.com\/watch?v=Qps93N1_Vkc","image":"https:\/\/cdn.discordapp.com\/attachments\/936396023478243389\/936396927589838888\/KronkArmor.png"},{"author":"kronk","url":"https:\/\/www.youtube.com\/watch?v=9bt2pdIDSFE","image":"https:\/\/cdn.discordapp.com\/attachments\/936396023478243389\/936396928336412682\/KronkRat.png"},{"author":"kronk","url":"https:\/\/www.youtube.com\/watch?v=iKaeTY30K5c","image":"https:\/\/cdn.discordapp.com\/attachments\/936396023478243389\/936396928646803536\/KronkArmor_2.png"},{"author":"kronk","url":"https:\/\/www.youtube.com\/watch?v=7AAC3cQ-3aQ","image":"https:\/\/cdn.discordapp.com\/attachments\/936396023478243389\/936396927883423824\/KronkRat_2.png"},{"author":"ren","url":"https:\/\/www.youtube.com\/watch?v=AcQU86ayXLM","image":"https:\/\/cdn.discordapp.com\/attachments\/936396023478243389\/936396549376864306\/Ren_2.png"},{"author":"ren","url":"https:\/\/www.youtube.com\/watch?v=JS6zsgFHQxo","image":"https:\/\/cdn.discordapp.com\/attachments\/936396023478243389\/936396549678833704\/Ren_3.png"},{"author":"ren","url":"https:\/\/www.youtube.com\/watch?v=nCair3HI9P8","image":"https:\/\/cdn.discordapp.com\/attachments\/936396023478243389\/936396550073110538\/Ren.png"},{"author":"marklar","url":"https:\/\/www.youtube.com\/watch?v=SyhkCUuosLQ","image":"https:\/\/cdn.discordapp.com\/attachments\/936396023478243389\/936396818760232960\/Marklar.png"},{"author":"marklar","url":"https:\/\/www.youtube.com\/watch?v=vAOEoHIwoNE","image":"https:\/\/cdn.discordapp.com\/attachments\/936396023478243389\/936396819020259368\/MarklarRat.png"},{"author":"ferazzle","url":"https:\/\/youtu.be\/ydEiu9MmEc4","image":"https:\/\/cdn.discordapp.com\/attachments\/936396023478243389\/936397340279971850\/Ferazzle.png"},{"author":"ferazzle","url":"https:\/\/youtu.be\/U_uvZxQLMok","image":"https:\/\/cdn.discordapp.com\/attachments\/936396023478243389\/936397352489598976\/Ferazzle_2.png"},{"author":"codito","url":"https:\/\/youtu.be\/G2DeINClfPQ","image":"https:\/\/cdn.discordapp.com\/attachments\/936396023478243389\/936399318410203208\/codito.png"},{"author":"greg","url":"https:\/\/youtu.be\/K3sZLgrjMBY","image":"https:\/\/cdn.discordapp.com\/attachments\/936396023478243389\/936397208994062356\/Greg.png"},{"author":"clinicallylazy","url":"https:\/\/youtu.be\/KC5e15eorVw","image":"https:\/\/cdn.discordapp.com\/attachments\/936396023478243389\/936396885260898314\/Lazy.png"},{"author":"jayy","url":"https:\/\/www.youtube.com\/watch?v=TzEeQ2eD1sE","image":"https:\/\/cdn.discordapp.com\/attachments\/936396023478243389\/936397164236636200\/Jayy.png"},{"author":"jayy","url":"https:\/\/www.youtube.com\/watch?v=VekilKG8LYA","image":"https:\/\/cdn.discordapp.com\/attachments\/936396023478243389\/936397164236636200\/Jayy.png"},{"author":"jayy","url":"https:\/\/www.youtube.com\/watch?v=sUVcJkMGcAE","image":"https:\/\/cdn.discordapp.com\/attachments\/936396023478243389\/936397164236636200\/Jayy.png"},{"author":"coco","url":"https:\/\/youtu.be\/xNKFOexNRE8","image":"https:\/\/cdn.discordapp.com\/attachments\/936396023478243389\/936397789875802174\/Coco.png"},{"author":"coco","url":"https:\/\/youtu.be\/4_4d48HpZQ8","image":"https:\/\/cdn.discordapp.com\/attachments\/936396023478243389\/936397789875802174\/Coco.png"},{"author":"vacant","url":"https:\/\/www.youtube.com\/watch?v=Z10qVRWxMqQ","image":"https:\/\/cdn.discordapp.com\/attachments\/936396023478243389\/936396403427659786\/Vacant.png"},{"author":"vacant","url":"https:\/\/www.youtube.com\/watch?v=ybe_blFQS_4","image":"https:\/\/cdn.discordapp.com\/attachments\/936396023478243389\/936396403427659786\/Vacant.png"},{"author":"smile","url":"https:\/\/www.youtube.com\/watch?v=UlOyO44Kxow","image":"https:\/\/cdn.discordapp.com\/attachments\/936396023478243389\/936396499632406609\/Smile.png"},{"author":"dresboni","url":"https:\/\/www.youtube.com\/watch?v=JmAWukebtHw","image":"https:\/\/cdn.discordapp.com\/attachments\/936396023478243389\/936397597634068510\/Dresboni4.png"},{"author":"dresboni","url":"https:\/\/www.youtube.com\/watch?v=HwhE1QuRUs8","image":"https:\/\/cdn.discordapp.com\/attachments\/936396023478243389\/936397598120640632\/Dresboni3.png"},{"author":"dresboni","url":"https:\/\/www.youtube.com\/watch?v=lwrXVKch2bY","image":"https:\/\/cdn.discordapp.com\/attachments\/936396023478243389\/936397598619754556\/Dresboni2.png"},{"author":"bryan","url":"https:\/\/www.youtube.com\/watch?v=0oZYdPnlHyo","image":"https:\/\/cdn.discordapp.com\/attachments\/936396023478243389\/936397969811464202\/Bryan.png"},{"author":"bryan","url":"https:\/\/youtu.be\/ZOEUMrrmgag","image":"https:\/\/cdn.discordapp.com\/attachments\/936396023478243389\/936397969811464202\/Bryan.png"},{"author":"vision","url":"https:\/\/www.youtube.com\/watch?v=-UqZbl-ZEk8","image":"https:\/\/cdn.discordapp.com\/attachments\/936396023478243389\/936396373136379954\/VisionFire.png"},{"author":"vision","url":"https:\/\/www.youtube.com\/watch?v=jaR2vsqdi1E","image":"https:\/\/cdn.discordapp.com\/attachments\/936396023478243389\/936396372859560036\/Vision.png"},{"author":"vision","url":"https:\/\/www.youtube.com\/watch?v=s9dqb2jiSEM","image":"https:\/\/cdn.discordapp.com\/attachments\/936396023478243389\/936396372859560036\/Vision.png"},{"author":"bane","url":"https:\/\/www.youtube.com\/watch?v=WodHFGhlH5w","image":"https:\/\/cdn.discordapp.com\/attachments\/936396023478243389\/936398039260733530\/Bane.png"},{"author":"cyclone","url":"https:\/\/www.youtube.com\/watch?v=IXmrj1MElKA","image":"https:\/\/cdn.discordapp.com\/attachments\/936396023478243389\/936397727917547600\/Cyclone.png"},{"author":"cyclone","url":"https:\/\/www.youtube.com\/watch?v=EgIWJOrgGdo","image":"https:\/\/cdn.discordapp.com\/attachments\/936396023478243389\/936397728160813126\/Cyclone_2.png"},{"author":"malthael","url":"https:\/\/www.youtube.com\/watch?v=rJ_WPY1IBY0","image":"https:\/\/cdn.discordapp.com\/attachments\/936396023478243389\/936396851534528542\/Malthael.png"},{"author":"malthael","url":"https:\/\/youtu.be\/GKXMUxZJk9k","image":"https:\/\/cdn.discordapp.com\/attachments\/936396023478243389\/936396851534528542\/Malthael.png"},{"author":"kllpdreams","url":"https:\/\/www.youtube.com\/watch?v=2iuDfnY3C6I","image":"https:\/\/cdn.discordapp.com\/attachments\/936396023478243389\/936397141553848341\/Kllp.png"},{"author":"kllpdreams","url":"https:\/\/www.youtube.com\/watch?v=COizRQLSRrE","image":"https:\/\/cdn.discordapp.com\/attachments\/936396023478243389\/936397141553848341\/Kllp.png"},{"author":"spaghettidan","url":"https:\/\/www.youtube.com\/watch?v=0jk-snGq_hw","image":"https:\/\/cdn.discordapp.com\/attachments\/936396023478243389\/936396455785156668\/SpaghettiDan.png"},{"author":"cologne","url":"https:\/\/www.youtube.com\/watch?v=YGZVtHLbeNY","image":"https:\/\/cdn.discordapp.com\/attachments\/936396023478243389\/936410305448263760\/Cologne.png"},{"author":"stauxie","url":"https:\/\/www.youtube.com\/watch?v=1G98RjWkM78","image":"https:\/\/cdn.discordapp.com\/attachments\/936396023478243389\/936396431193931786\/Stauxie.png"},{"author":"jazz","url":"https:\/\/www.youtube.com\/watch?v=HuAPpjk3ZDM","image":"https:\/\/cdn.discordapp.com\/attachments\/936396023478243389\/936407895707373578\/Jazz.png"},{"author":"jazz","url":"https:\/\/www.youtube.com\/watch?v=IIJbwAZXENk","image":"https:\/\/cdn.discordapp.com\/attachments\/936396023478243389\/936407900287545404\/Jazz2.png"},{"author":"nexxy","url":"https:\/\/www.youtube.com\/watch?v=Z7SnabtWVd4","image":"https:\/\/cdn.discordapp.com\/attachments\/936396023478243389\/936396621858607104\/Nexxy.png"},{"author":"nexxy","url":"https:\/\/www.youtube.com\/watch?v=SvihWBT44sA","image":"https:\/\/cdn.discordapp.com\/attachments\/936396023478243389\/936396621858607104\/Nexxy.png"},{"author":"bmop","url":"https:\/\/www.youtube.com\/watch?v=LuQjns-6V04","image":"https:\/\/cdn.discordapp.com\/attachments\/936396023478243389\/936398002912919602\/Bmop.png"},{"author":"grandpa","url":"https:\/\/www.youtube.com\/watch?v=n4WqqRoUCxc","image":"https:\/\/cdn.discordapp.com\/attachments\/936396023478243389\/936397296994770975\/Grandpa.png"},{"author":"grandpa","url":"https:\/\/www.youtube.com\/watch?v=VX0n4AoUWvY","image":"https:\/\/cdn.discordapp.com\/attachments\/936396023478243389\/936397296994770975\/Grandpa.png"}]